{"data":[{"ic":null,"date":"2025-07-28T17:41:44.274","name":"New","type":"Miscellaneous","uuid":"1db58b2d-e23d-4f5d-96b7-cc8cd7d72718","acres":null,"fuels":null,"inc_num":"4281","fire_num":null,"latitude":null,"location":null,"longitude":null,"resources":[null],"webComment":null,"fire_status":"{\"out\": null, \"contain\": null, \"control\": null}","fiscal_data":"{\"inc_num\": \"4281\", \"abcd_misc\": null, \"fire_code\": null, \"wfdssunit\": \"CAKNF\", \"fs_job_code\": null, \"fs_override\": null, \"fiscal_comments\": null, \"state_fiscal_code\": null}"},{"ic":null,"date":"2025-06-17T16:20:57.826","name":"SRF-Smoke check","type":"Miscellaneous","uuid":"3180a873-64e2-4faf-8861-5a721506adea","acres":null,"fuels":null,"inc_num":"4278","fire_num":null,"latitude":"41.674958","location":null,"longitude":"123.022864","resources":[null],"webComment":null,"fire_status":"{\"out\": null, \"contain\": null, \"control\": null}","fiscal_data":"{\"inc_num\": \"4278\", \"abcd_misc\": null, \"fire_code\": null, \"wfdssunit\": \"CAKNF\", \"fs_job_code\": null, \"fs_override\": null, \"fiscal_comments\": null, \"state_fiscal_code\": null}"},{"ic":null,"date":"2025-06-10T23:10:14.466","name":"HERD","type":"Miscellaneous","uuid":"5111b2dd-f0fc-432a-b70d-d149ea8cdc61","acres":null,"fuels":null,"inc_num":"37","fire_num":null,"latitude":"41.636296","location":null,"longitude":"122.235500","resources":[null],"webComment":null,"fire_status":"{\"out\": null, \"contain\": null, \"control\": null}","fiscal_data":"{\"inc_num\": \"37\", \"abcd_misc\": null, \"fire_code\": null, \"wfdssunit\": \"CAKNF\", \"fs_job_code\": null, \"fs_override\": null, \"fiscal_comments\": null, \"state_fiscal_code\": null}"},{"ic":null,"date":"2025-09-02T09:03:00.177","name":"New","type":"Miscellaneous","uuid":"65d157fd-76be-45a8-b6d8-1dadebf294f9","acres":null,"fuels":null,"inc_num":"4287","fire_num":null,"latitude":null,"location":null,"longitude":null,"resources":[null],"webComment":null,"fire_status":"{\"out\": null, \"contain\": null, \"control\": null}","fiscal_data":"{\"inc_num\": \"4287\", \"abcd_misc\": null, \"fire_code\": null, \"wfdssunit\": \"CAKNF\", \"fs_job_code\": null, \"fs_override\": null, \"fiscal_comments\": null, \"state_fiscal_code\": null}"},{"ic":null,"date":"2025-08-22T18:50:19.717","name":"New","type":"Miscellaneous","uuid":"6772d5f4-98d2-47af-9bd5-4fbf7d34e5cc","acres":null,"fuels":null,"inc_num":"4285","fire_num":null,"latitude":null,"location":null,"longitude":null,"resources":[null],"webComment":null,"fire_status":"{\"out\": null, \"contain\": null, \"control\": null}","fiscal_data":"{\"inc_num\": \"4285\", \"abcd_misc\": null, \"fire_code\": null, \"wfdssunit\": \"CAKNF\", \"fs_job_code\": null, \"fs_override\": null, \"fiscal_comments\": null, \"state_fiscal_code\": null}"},{"ic":null,"date":"2025-09-17T17:40:03.422","name":"New","type":"Miscellaneous","uuid":"696bd081-9fee-4e2a-9128-b99eed76ab6d","acres":null,"fuels":null,"inc_num":"4288","fire_num":null,"latitude":null,"location":null,"longitude":null,"resources":[null],"webComment":null,"fire_status":"{\"out\": null, \"contain\": null, \"control\": null}","fiscal_data":"{\"inc_num\": \"4288\", \"abcd_misc\": null, \"fire_code\": null, \"wfdssunit\": \"CAKNF\", \"fs_job_code\": null, \"fs_override\": null, \"fiscal_comments\": null, \"state_fiscal_code\": null}"},{"ic":null,"date":"2025-06-08T11:03:04.698","name":"Drylake DIST","type":"Miscellaneous","uuid":"927a0ce4-28a7-4eef-963d-830b016b7aba","acres":null,"fuels":null,"inc_num":"35","fire_num":null,"latitude":"41.819112","location":null,"longitude":"121.827393","resources":[null],"webComment":null,"fire_status":"{\"out\": null, \"contain\": null, \"control\": null}","fiscal_data":"{\"inc_num\": \"35\", \"abcd_misc\": null, \"fire_code\": null, \"wfdssunit\": \"CAKNF\", \"fs_job_code\": null, \"fs_override\": null, \"fiscal_comments\": null, \"state_fiscal_code\": null}"},{"ic":null,"date":"2025-06-30T14:55:08.75","name":"New","type":"Miscellaneous","uuid":"a5d5735d-4a44-43a2-8e8a-ce5946fc83aa","acres":null,"fuels":null,"inc_num":"4279","fire_num":null,"latitude":null,"location":null,"longitude":null,"resources":[null],"webComment":null,"fire_status":"{\"out\": null, \"contain\": null, \"control\": null}","fiscal_data":"{\"inc_num\": \"4279\", \"abcd_misc\": null, \"fire_code\": null, \"wfdssunit\": \"CAKNF\", \"fs_job_code\": null, \"fs_override\": null, \"fiscal_comments\": null, \"state_fiscal_code\": null}"},{"ic":null,"date":"2025-08-20T17:45:51.791","name":"New","type":"Miscellaneous","uuid":"af108942-1f2d-440d-a33b-08209a369b52","acres":null,"fuels":null,"inc_num":"4284","fire_num":null,"latitude":null,"location":null,"longitude":null,"resources":[null],"webComment":null,"fire_status":"{\"out\": null, \"contain\": null, \"control\": null}","fiscal_data":"{\"inc_num\": \"4284\", \"abcd_misc\": null, \"fire_code\": null, \"wfdssunit\": \"CAKNF\", \"fs_job_code\": null, \"fs_override\": null, \"fiscal_comments\": null, \"state_fiscal_code\": null}"},{"ic":null,"date":"2025-08-04T09:47:00.548","name":"New","type":"Miscellaneous","uuid":"af45e8bc-5c77-4bb9-b447-5a0e9e294fca","acres":null,"fuels":null,"inc_num":"4283","fire_num":null,"latitude":null,"location":null,"longitude":null,"resources":[null],"webComment":null,"fire_status":"{\"out\": null, \"contain\": null, \"control\": null}","fiscal_data":"{\"inc_num\": \"4283\", \"abcd_misc\": null, \"fire_code\": null, \"wfdssunit\": \"CAKNF\", \"fs_job_code\": null, \"fs_override\": null, \"fiscal_comments\": null, \"state_fiscal_code\": null}"}],"retrieved":"2025-11-07T22:43:36.933148","webComment":null}